CaozuoxitongSikao/README.md
CaozuoxitongSikao/__init__.py
CaozuoxitongSikao/__main__.py
CaozuoxitongSikao/file.epub
CaozuoxitongSikao/index.html
CaozuoxitongSikao/css/__init__.py
CaozuoxitongSikao/css/annotations.css
CaozuoxitongSikao/css/main.css
CaozuoxitongSikao/css/normalize.css
CaozuoxitongSikao/css/popup.css
CaozuoxitongSikao/font/__init__.py
CaozuoxitongSikao/font/fontello.eot
CaozuoxitongSikao/font/fontello.svg
CaozuoxitongSikao/font/fontello.ttf
CaozuoxitongSikao/font/fontello.woff
CaozuoxitongSikao/img/__init__.py
CaozuoxitongSikao/img/annotator-glyph-sprite.png
CaozuoxitongSikao/img/annotator-icon-sprite.png
CaozuoxitongSikao/img/apple-touch-icon.png
CaozuoxitongSikao/img/cancelfullscreen.png
CaozuoxitongSikao/img/close.png
CaozuoxitongSikao/img/fullscreen.png
CaozuoxitongSikao/img/loader.gif
CaozuoxitongSikao/img/menu-icon.png
CaozuoxitongSikao/img/save.png
CaozuoxitongSikao/img/saved.png
CaozuoxitongSikao/img/settings-s.png
CaozuoxitongSikao/img/settings.png
CaozuoxitongSikao/img/star.png
CaozuoxitongSikao/js/__init__.py
CaozuoxitongSikao/js/epub.js
CaozuoxitongSikao/js/epub.min.js
CaozuoxitongSikao/js/epub.min.map
CaozuoxitongSikao/js/hooks.min.js
CaozuoxitongSikao/js/hooks.min.map
CaozuoxitongSikao/js/reader.js
CaozuoxitongSikao/js/reader.js.map
CaozuoxitongSikao/js/reader.min.js
CaozuoxitongSikao/js/reader.min.map
CaozuoxitongSikao/js/hooks/__init__.py
CaozuoxitongSikao/js/hooks/extensions/__init__.py
CaozuoxitongSikao/js/hooks/extensions/highlight.js
CaozuoxitongSikao/js/libs/__init__.py
CaozuoxitongSikao/js/libs/jquery.min.js
CaozuoxitongSikao/js/libs/localforage.min.js
CaozuoxitongSikao/js/libs/screenfull.js
CaozuoxitongSikao/js/libs/screenfull.min.js
CaozuoxitongSikao/js/libs/zip.min.js
CaozuoxitongSikao/js/plugins/__init__.py
CaozuoxitongSikao/js/plugins/hypothesis.js
CaozuoxitongSikao/js/plugins/search.js
caozuoxitong_sikao-2024.3.1.0.dist-info/METADATA
caozuoxitong_sikao-2024.3.1.0.dist-info/WHEEL
caozuoxitong_sikao-2024.3.1.0.dist-info/entry_points.txt
caozuoxitong_sikao-2024.3.1.0.dist-info/top_level.txt
caozuoxitong_sikao-2024.3.1.0.dist-info/RECORD
